{
  "title": "Ch 7.4 вЂ” Objects Working Together: Character Buys Items",
  "description": "Practice making two classes interact with each other.\n\nYou'll build an Item class and a Character class. The Character\ncan check if it can afford an Item and buy it.\n\nв”Ђв”Ђв”Ђв”Ђв”Ђв”Ђв”Ђв”Ђв”Ђв”Ђв”Ђв”Ђв”Ђв”Ђв”Ђв”Ђв”Ђв”Ђв”Ђв”Ђв”Ђв”Ђв”Ђв”Ђв”Ђв”Ђв”Ђв”Ђв”Ђв”Ђв”Ђв”Ђв”Ђв”Ђв”Ђв”Ђв”Ђв”Ђв”Ђв”Ђв”Ђв”Ђв”Ђв”Ђв”Ђв”Ђ\nClass: Item (package-private, i.e. no public keyword)\nв”Ђв”Ђв”Ђв”Ђв”Ђв”Ђв”Ђв”Ђв”Ђв”Ђв”Ђв”Ђв”Ђв”Ђв”Ђв”Ђв”Ђв”Ђв”Ђв”Ђв”Ђв”Ђв”Ђв”Ђв”Ђв”Ђв”Ђв”Ђв”Ђв”Ђв”Ђв”Ђв”Ђв”Ђв”Ђв”Ђв”Ђв”Ђв”Ђв”Ђв”Ђв”Ђв”Ђв”Ђв”Ђв”Ђ\n  Private fields:\n    вЂў String name\n    вЂў int price\n\n  Constructor:  Item(String name, int price)\n    вЂ” Use this. Clamp price to >= 0.\n\n  Getters:\n    вЂў String getName()\n    вЂў int getPrice()\n\nв”Ђв”Ђв”Ђв”Ђв”Ђв”Ђв”Ђв”Ђв”Ђв”Ђв”Ђв”Ђв”Ђв”Ђв”Ђв”Ђв”Ђв”Ђв”Ђв”Ђв”Ђв”Ђв”Ђв”Ђв”Ђв”Ђв”Ђв”Ђв”Ђв”Ђв”Ђв”Ђв”Ђв”Ђв”Ђв”Ђв”Ђв”Ђв”Ђв”Ђв”Ђв”Ђв”Ђв”Ђв”Ђв”Ђ\nClass: Character (public)\nв”Ђв”Ђв”Ђв”Ђв”Ђв”Ђв”Ђв”Ђв”Ђв”Ђв”Ђв”Ђв”Ђв”Ђв”Ђв”Ђв”Ђв”Ђв”Ђв”Ђв”Ђв”Ђв”Ђв”Ђв”Ђв”Ђв”Ђв”Ђв”Ђв”Ђв”Ђв”Ђв”Ђв”Ђв”Ђв”Ђв”Ђв”Ђв”Ђв”Ђв”Ђв”Ђв”Ђв”Ђв”Ђв”Ђ\n  Private fields:\n    вЂў String name\n    вЂў int gold\n\n  Constructor:  Character(String name, int gold)\n    вЂ” Use this. Clamp gold to >= 0.\n\n  Getters:\n    вЂў String getName()\n    вЂў int getGold()\n\n  Methods:\n    вЂў boolean canAfford(Item item)\n        returns true if gold >= item.getPrice()\n\n    вЂў String buyItem(Item item)\n        If canAfford(item):\n          вЂ” subtract the item's price from gold\n          вЂ” return: \"<n> buys <itemName> for <price> gold.\"\n          вЂ” example: \"Aria buys Health Potion for 20 gold.\"\n        If NOT affordable:\n          вЂ” do NOT change gold\n          вЂ” return: \"<n> cannot afford <itemName>.\"\n          вЂ” example: \"Aria cannot afford Sword.\"\n\n    вЂў String status()\n        returns: \"<n> has <gold> gold.\"\n        example: \"Aria has 30 gold.\"\n\nв”Ђв”Ђв”Ђв”Ђв”Ђв”Ђв”Ђв”Ђв”Ђв”Ђв”Ђв”Ђв”Ђв”Ђв”Ђв”Ђв”Ђв”Ђв”Ђв”Ђв”Ђв”Ђв”Ђв”Ђв”Ђв”Ђв”Ђв”Ђв”Ђв”Ђв”Ђв”Ђв”Ђв”Ђв”Ђв”Ђв”Ђв”Ђв”Ђв”Ђв”Ђв”Ђв”Ђв”Ђв”Ђв”Ђ\nHINTS\nв”Ђв”Ђв”Ђв”Ђв”Ђв”Ђв”Ђв”Ђв”Ђв”Ђв”Ђв”Ђв”Ђв”Ђв”Ђв”Ђв”Ђв”Ђв”Ђв”Ђв”Ђв”Ђв”Ђв”Ђв”Ђв”Ђв”Ђв”Ђв”Ђв”Ђв”Ђв”Ђв”Ђв”Ђв”Ђв”Ђв”Ђв”Ђв”Ђв”Ђв”Ђв”Ђв”Ђв”Ђв”Ђв”Ђ\nвЂў Item must NOT be public (only one public class per file).\n  Write it above or below Character with no access modifier.\nвЂў In buyItem(), call item.getName() and item.getPrice() вЂ”\n  Character interacts with Item through its public methods.\nвЂў buyItem() should RETURN a String, not print it.",
  "student_filename": "Character.java",
  "starter_code": "// Item class вЂ” NOT public (package-private)\nclass Item {\n    // TODO: private fields, constructor, getters\n}\n\n// Character class вЂ” public\npublic class Character {\n    // TODO: private fields (name, gold)\n\n    // TODO: Constructor вЂ” Character(String name, int gold)\n    //   Clamp gold >= 0\n\n    // TODO: Getters вЂ” getName(), getGold()\n\n    // TODO: boolean canAfford(Item item)\n\n    // TODO: String buyItem(Item item)\n    //   If affordable: subtract price, return \"<n> buys <item> for <price> gold.\"\n    //   If not: return \"<n> cannot afford <item>.\"\n\n    // TODO: String status()\n    //   returns \"<n> has <gold> gold.\"\n}\n",
  "support_files": [],
  "test_filename": "TestRunner.java",
  "test_code": "public class TestRunner {\n    static int passed = 0;\n    static int failed = 0;\n\n    public static void main(String[] args) {\n\n        // в”Ђв”Ђ Item basics в”Ђв”Ђ\n        try {\n            Item potion = new Item(\"Health Potion\", 20);\n            check(\"Item.getName()\",\n                  \"Health Potion\", potion.getName());\n        } catch (Exception e) { fail(\"Item.getName()\", e); }\n\n        try {\n            Item potion = new Item(\"Health Potion\", 20);\n            check(\"Item.getPrice()\",\n                  \"20\", String.valueOf(potion.getPrice()));\n        } catch (Exception e) { fail(\"Item.getPrice()\", e); }\n\n        try {\n            Item bad = new Item(\"Cursed Ring\", -5);\n            check(\"Item price clamps negative to 0\",\n                  \"0\", String.valueOf(bad.getPrice()));\n        } catch (Exception e) { fail(\"Item price clamp\", e); }\n\n        // в”Ђв”Ђ Character basics в”Ђв”Ђ\n        try {\n            Character hero = new Character(\"Aria\", 50);\n            check(\"Character.getName()\",\n                  \"Aria\", hero.getName());\n        } catch (Exception e) { fail(\"Character.getName()\", e); }\n\n        try {\n            Character hero = new Character(\"Aria\", 50);\n            check(\"Character.getGold()\",\n                  \"50\", String.valueOf(hero.getGold()));\n        } catch (Exception e) { fail(\"Character.getGold()\", e); }\n\n        try {\n            Character broke = new Character(\"Bob\", -10);\n            check(\"Character gold clamps negative to 0\",\n                  \"0\", String.valueOf(broke.getGold()));\n        } catch (Exception e) { fail(\"Character gold clamp\", e); }\n\n        // в”Ђв”Ђ canAfford в”Ђв”Ђ\n        try {\n            Character hero = new Character(\"Aria\", 50);\n            Item potion = new Item(\"Potion\", 20);\n            check(\"canAfford() вЂ” has enough\",\n                  \"true\", String.valueOf(hero.canAfford(potion)));\n        } catch (Exception e) { fail(\"canAfford() true\", e); }\n\n        try {\n            Character hero = new Character(\"Aria\", 10);\n            Item sword = new Item(\"Sword\", 25);\n            check(\"canAfford() вЂ” not enough\",\n                  \"false\", String.valueOf(hero.canAfford(sword)));\n        } catch (Exception e) { fail(\"canAfford() false\", e); }\n\n        try {\n            Character hero = new Character(\"Aria\", 20);\n            Item potion = new Item(\"Potion\", 20);\n            check(\"canAfford() вЂ” exact amount\",\n                  \"true\", String.valueOf(hero.canAfford(potion)));\n        } catch (Exception e) { fail(\"canAfford() exact\", e); }\n\n        // в”Ђв”Ђ buyItem вЂ” success в”Ђв”Ђ\n        try {\n            Character hero = new Character(\"Aria\", 50);\n            Item potion = new Item(\"Health Potion\", 20);\n            String result = hero.buyItem(potion);\n            check(\"buyItem() success message\",\n                  \"Aria buys Health Potion for 20 gold.\", result);\n        } catch (Exception e) { fail(\"buyItem() success message\", e); }\n\n        try {\n            Character hero = new Character(\"Aria\", 50);\n            Item potion = new Item(\"Health Potion\", 20);\n            hero.buyItem(potion);\n            check(\"buyItem() subtracts gold\",\n                  \"30\", String.valueOf(hero.getGold()));\n        } catch (Exception e) { fail(\"buyItem() subtracts gold\", e); }\n\n        // в”Ђв”Ђ buyItem вЂ” failure в”Ђв”Ђ\n        try {\n            Character hero = new Character(\"Aria\", 10);\n            Item sword = new Item(\"Sword\", 25);\n            String result = hero.buyItem(sword);\n            check(\"buyItem() failure message\",\n                  \"Aria cannot afford Sword.\", result);\n        } catch (Exception e) { fail(\"buyItem() failure message\", e); }\n\n        try {\n            Character hero = new Character(\"Aria\", 10);\n            Item sword = new Item(\"Sword\", 25);\n            hero.buyItem(sword);\n            check(\"buyItem() failure doesn't change gold\",\n                  \"10\", String.valueOf(hero.getGold()));\n        } catch (Exception e) { fail(\"buyItem() failure gold unchanged\", e); }\n\n        // в”Ђв”Ђ Multiple purchases в”Ђв”Ђ\n        try {\n            Character hero = new Character(\"Aria\", 40);\n            Item p = new Item(\"Potion\", 15);\n            Item s = new Item(\"Shield\", 30);\n            hero.buyItem(p);   // 40 - 15 = 25\n            String r = hero.buyItem(s);  // 25 < 30 в†’ fail\n            check(\"Second buy fails (not enough gold left)\",\n                  \"Aria cannot afford Shield.\", r);\n        } catch (Exception e) { fail(\"Multiple purchases\", e); }\n\n        // в”Ђв”Ђ status() в”Ђв”Ђ\n        try {\n            Character hero = new Character(\"Aria\", 50);\n            check(\"status()\",\n                  \"Aria has 50 gold.\", hero.status());\n        } catch (Exception e) { fail(\"status()\", e); }\n\n        try {\n            Character hero = new Character(\"Aria\", 50);\n            hero.buyItem(new Item(\"Potion\", 20));\n            check(\"status() after purchase\",\n                  \"Aria has 30 gold.\", hero.status());\n        } catch (Exception e) { fail(\"status() after purchase\", e); }\n\n        // в”Ђв”Ђ Encapsulation в”Ђв”Ђ\n        try {\n            java.lang.reflect.Field f = Character.class.getDeclaredField(\"gold\");\n            check(\"Character.gold is private\", \"true\",\n                  String.valueOf(java.lang.reflect.Modifier.isPrivate(f.getModifiers())));\n        } catch (NoSuchFieldException e) {\n            fail(\"Character.gold field exists\", new Exception(\"Field 'gold' not found\"));\n        } catch (Exception e) { fail(\"Character.gold is private\", e); }\n\n        try {\n            java.lang.reflect.Field f = Item.class.getDeclaredField(\"price\");\n            check(\"Item.price is private\", \"true\",\n                  String.valueOf(java.lang.reflect.Modifier.isPrivate(f.getModifiers())));\n        } catch (NoSuchFieldException e) {\n            fail(\"Item.price field exists\", new Exception(\"Field 'price' not found\"));\n        } catch (Exception e) { fail(\"Item.price is private\", e); }\n    }\n\n    static void check(String label, String expected, String actual) {\n        if (expected.equals(actual)) {\n            System.out.println(\"PASS: \" + label); passed++;\n        } else {\n            System.out.println(\"FAIL: \" + label\n                + \" \\u2014 expected \\\"\" + expected\n                + \"\\\" but got \\\"\" + actual + \"\\\"\"); failed++;\n        }\n    }\n    static void fail(String label, Exception e) {\n        System.out.println(\"FAIL: \" + label + \" \\u2014 \" + e.getMessage()); failed++;\n    }\n}\n"
}
